foundation_python/__init__.py
foundation_python/logger.py
foundation_python/queue/__init__.py
foundation_python/queue/escalation.py
foundation_python/queue/queue_manager.py
foundation_python/util/__init__.py
foundation_python/util/common.py
foundation_python-1.0.6.dist-info/METADATA
foundation_python-1.0.6.dist-info/WHEEL
foundation_python-1.0.6.dist-info/RECORD
