Metadata-Version: 2.1
Name: foundation-python
Version: 1.0.6
Summary: 
Author: bai ying
Author-email: cn.baiying@gmail.com
Requires-Python: >=3.11,<4.0
Classifier: Programming Language :: Python :: 3
Classifier: Programming Language :: Python :: 3.11
Classifier: Programming Language :: Python :: 3.12
Classifier: Programming Language :: Python :: 3.13
Requires-Dist: bullmq (>=2.9.3,<3.0.0)
Requires-Dist: python-dotenv (>=1.0.1,<2.0.0)
Requires-Dist: pyyaml (>=6.0.2,<7.0.0)
Requires-Dist: redis (>=5.0.8,<6.0.0)
Requires-Dist: shortuuid (>=1.0.13,<2.0.0)
